Practical5/HandIn/tsc.v
/* Thomas and Charlie's TSC module
*  4/30/2024
*/



module tsc ( 
          
    // -----declaring the ADC comms         
    input wire rdy,      // Ready signal from ADC
    input wire [7:0] dat, // Data input from the ADC array   
    
    output reg req,      // Request signal to ADC

    // -----declaring the ext device comms
    input wire clk,
    input wire start,
    input wire reset,
    input wire SBF,
    
    output reg CD, 
    output reg TRD,
    output reg SD //serial data output
    //test


);
    //---- declaring the internal registers

    reg [31:0] timer;
    reg [0:7] trigVal =8'hD5; // hardcoded value for trigger -> see prac 5
   
    reg [31:0] trigTM; //this will store the time when triggered
    reg [0:7] ringBuf [0:31];// ring buffer of 32 bytes
    reg [0:4]  head; // head and tail for FIFO
    reg [0:4] tail;

    reg [0:3] index; // this is the index to send out 1 bit at a time from SD
    reg dataAvaliable; // this will be triggered if that data is available to read from ADC
    
    //making local params for readability of the states
    localparam  RESET = 3'b100,
                IDLE = 3'b000,
                RECORD = 3'b001,
                TRIGGERED = 3'b010,
                SENDBUFFER = 3'b011;
                
    
    //setting the current state into the IDLE
    reg [3:0] currentState = IDLE;

    //startup conditions
    initial
        begin
           currentState <= RESET;
           timer <= 32'h00; 
           index <= 0;
           SD <= 0;
           req <= 0;
           
        end


    //Reset on clock, not sure if we need this but need to transition states using this always@() style
    always@(posedge reset) begin
        currentState <= RESET;
        //resets all the values
        currentState <= IDLE;
        head <= 5'h0;
        tail <= 5'h1;
        TRD <= 1'b0;
        CD <= 1'b0;
        req <= 0;
        dataAvaliable = 0;
    end
    always@(posedge rdy)begin
        dataAvaliable = 1'b1; // you are allowed to read from ADC
    end

    always@(posedge start) begin //edge trigger state shifter
        currentState <= RECORD;
    end

    always@(posedge SBF) begin //edge trigger state shifter
        currentState <= SENDBUFFER;
    end

    always@(posedge clk) begin
        case (currentState)
            IDLE: begin
                req <=0; // do nothing except tell the ADC you want nothing
            end
            RECORD: begin
                req <= 1'b1; // ask for adc to send data
                if(dataAvaliable) begin // wait for data to become available from ADC (should be super fast)
                    timer <= timer +1; // increment the clock
                    tail <= (tail+1)%32;// increment the tail
                    ringBuf[tail] <= dat; // store the data in the ring buffer    
                    if(head === tail) begin // if it has gone around the loop shift (don't let the tail get eaten by the head)
                        head <= (head +1) % 32;
                    end    
                    if(dat > trigVal) begin //now need to shift into a new state if the trigger value is high enough
                        trigTM <= timer;
                        currentState <= TRIGGERED; // move the triggered
                    end   
                end
            end
            TRIGGERED: begin
                //needs to store the next 16 values from adc
                if(dataAvaliable == 1) begin
                    timer <= timer +1;//increment the timer
                    if((timer - trigTM)< 16) begin // if it hasn't yet stored 16 more data bits store one more
                        ringBuf[tail] <= dat;
                        tail <= tail+ 1;   
                    end
                    else begin
                        currentState <= IDLE;
                        TRD = 1'b1; // output that you have been triggered
                        SD <= 1'b0; //start condition
                        CD <= 1'b0; // not complete
                    end
                    if(head == tail) begin // if it has gone around the loop shift 
                            head <= (head +1) % 32;
                    end
                end
            end
            SENDBUFFER: begin //also see the posedge clk to get a full understand how the data is sent out
            //needs to send ring buff out via SD Lin               
                if(tail!=head) begin // if havn't sent out whole buffer keep sending
                    if(index < 8) begin // if havent completed a byte yet keep trying
                        SD <= ringBuf[tail][index]; 
                        //sendsout a bit from the ring buf
                        index <= index +1;
                    end    
                    else begin //once sent out a byte -> go to the next item
                        SD <=1; // sets SD to zero at the start of every byte
                        index <= 0; //resetting to the starts of a vyte
                        if(tail ==0) begin// this will allow the buffer to loop around and not go negative
                            tail <=32;
                        end
                        tail <= tail -1; // decrementing the tail
                    end
                end
                else begin
                    CD <= 1'b1; //data sent through
                    currentState <= IDLE;
                end
            end    

        endcase 
    end
    always@(negedge clk) begin
        if(currentState == SENDBUFFER) begin
            SD <= 0;
            //sends a low at the start of every bit
        end
    end
endmodule;

Practical5/HandIn/TSC_TestBench2.v
`include "tsc.v"
`timescale 1ns / 1ps

module tSC_TestBench2();
integer i;
parameter CLK_PERIOD = 10; // Clock period in ns

// Declare inputs as regs and outputs as wires
//From ADC
reg rdy;
reg [7:0] dat;
//To ADC
wire req;

//External inputs
reg clk;
reg start;
reg reset;
reg SBF;
//External Outputs
wire CD;
wire TRD;
wire SD;


//ADC DATA
reg [0:7] adc_data [0:15];

    

// Instantiate ADC module
tsc tsc_init (
    .rdy(rdy),
    .dat(dat),
    .req(req),
    .clk(clk),
    .start(start),
    .reset(reset),
    .SBF(SBF),
    .CD(CD),
    .TRD(TRD),
    .SD(SD)
);

// Initialize all variables
initial begin 
  $display("Started");
  $dumpfile("Test3.vcd");
  $dumpvars(0,tSC_TestBench2);
  	
  //set intial values of thingies
  rdy = 0;
  dat = 8'h00;
  i = 0;
  clk = 0;
  start = 0;
  reset =0;
  SBF =0;
  dat = 0;
// adc dataValues
  adc_data[ 0] = 8'h00;
adc_data[ 1] = 8'h0A;
adc_data[ 2] = 8'h99;
adc_data[ 3] = 8'h9B;
adc_data[ 4] = 8'h93;
adc_data[ 5] = 8'hD5; // this should trigger it 
adc_data[ 6] = 8'h97;
adc_data[ 7] = 8'h90;
adc_data[ 8] = 8'h9F;
adc_data[ 9] = 8'hD7;
adc_data[10] = 8'h8D;
adc_data[11] = 8'h9C;
adc_data[12] = 8'h85;
adc_data[13] = 8'h8A;
adc_data[14] = 8'h91;
adc_data[15] = 8'h8C;

  //checking the operation of the states
  #10 reset =1; //reseting
  #10 reset = 0;
  #10 start = 1;
  #10 start = 0;  //go into RECORD mode (001)
  #1 rdy = 1; // ADC pulsing the ready line
  #1 rdy = 0;
  //sending a bunch of data to (as if it was the ADC)
  while(req ==1) begin
    #10 dat = adc_data[i%16];
    i<= i+1;
  end
  
  #10 SBF =1; // go to send buf mode
  $display("Finished");
  #1200 $finish;
  
end

// Clock generator
always begin
  #2 clk = ~clk; // Toggle clock every 5 ticks
end

// Connect DUT to test bench
    
endmodule

Practical5/HandIn/Test3.vcd
$date
	Tue Apr 30 15:04:10 2024
$end
$version
	Icarus Verilog
$end
$timescale
	1ps
$end
$scope module tSC_TestBench2 $end
$var wire 1 ! req $end
$var wire 1 " TRD $end
$var wire 1 # SD $end
$var wire 1 $ CD $end
$var parameter 32 % CLK_PERIOD $end
$var reg 1 & SBF $end
$var reg 1 ' clk $end
$var reg 8 ( dat [7:0] $end
$var reg 1 ) rdy $end
$var reg 1 * reset $end
$var reg 1 + start $end
$var integer 32 , i [31:0] $end
$scope module tsc_init $end
$var wire 1 & SBF $end
$var wire 1 ' clk $end
$var wire 8 - dat [7:0] $end
$var wire 1 ) rdy $end
$var wire 1 * reset $end
$var wire 1 + start $end
$var parameter 3 . IDLE $end
$var parameter 3 / RECORD $end
$var parameter 3 0 RESET $end
$var parameter 3 1 SENDBUFFER $end
$var parameter 3 2 TRIGGERED $end
$var reg 1 $ CD $end
$var reg 1 # SD $end
$var reg 1 " TRD $end
$var reg 4 3 currentState [3:0] $end
$var reg 1 4 dataAvaliable $end
$var reg 5 5 head [0:4] $end
$var reg 4 6 index [0:3] $end
$var reg 1 ! req $end
$var reg 5 7 tail [0:4] $end
$var reg 32 8 timer [31:0] $end
$var reg 32 9 trigTM [31:0] $end
$var reg 8 : trigVal [0:7] $end
$upscope $end
$upscope $end
$enddefinitions $end
$comment Show the parameter values. $end
$dumpall
b10 2
b11 1
b100 0
b1 /
b0 .
b1010 %
$end
#0
$dumpvars
b11010101 :
bx 9
b0 8
bx 7
b0 6
bx 5
x4
b100 3
b0 -
b0 ,
0+
0*
0)
b0 (
0'
0&
x$
0#
x"
0!
$end
#2000
1'
#4000
0'
#6000
1'
#8000
0'
#10000
0$
0"
b1 7
b0 5
b0 3
04
1'
1*
#12000
0'
#14000
1'
#16000
0'
#18000
1'
#20000
0'
0*
#22000
1'
#24000
0'
#26000
1'
#28000
0'
#30000
b1 3
1'
1+
#32000
0'
#34000
1!
1'
#36000
0'
#38000
1'
#40000
0'
0+
#41000
14
1)
#42000
b10 7
b1 8
0)
1'
#44000
0'
#46000
b11 7
b10 8
1'
#48000
0'
#50000
b100 7
b11 8
1'
#52000
b1 ,
0'
#54000
b101 7
b100 8
1'
#56000
0'
#58000
b110 7
b101 8
1'
#60000
0'
#62000
b111 7
b110 8
b10 ,
1'
b1010 (
b1010 -
#64000
0'
#66000
b1000 7
b111 8
1'
#68000
0'
#70000
b1001 7
b1000 8
1'
#72000
b11 ,
0'
b10011001 (
b10011001 -
#74000
b1010 7
b1001 8
1'
#76000
0'
#78000
b1011 7
b1010 8
1'
#80000
0'
#82000
b1100 7
b1011 8
b100 ,
1'
b10011011 (
b10011011 -
#84000
0'
#86000
b1101 7
b1100 8
1'
#88000
0'
#90000
b1110 7
b1101 8
1'
#92000
b101 ,
0'
b10010011 (
b10010011 -
#94000
b1111 7
b1110 8
1'
#96000
0'
#98000
b10000 7
b1111 8
1'
#100000
0'
#102000
b10001 7
b10000 8
b110 ,
1'
b11010101 (
b11010101 -
#104000
0'
#106000
b10010 7
b10001 8
1'
#108000
0'
#110000
b10011 7
b10010 8
1'
#112000
b111 ,
0'
b10010111 (
b10010111 -
#114000
b10100 7
b10011 8
1'
#116000
0'
#118000
b10101 7
b10100 8
1'
#120000
0'
#122000
b10110 7
b10101 8
b1000 ,
1'
b10010000 (
b10010000 -
#124000
0'
#126000
b10111 7
b10110 8
1'
#128000
0'
#130000
b11000 7
b10111 8
1'
#132000
b1001 ,
0'
b10011111 (
b10011111 -
#134000
b11001 7
b11000 8
1'
#136000
0'
#138000
b11010 7
b11001 8
1'
#140000
0'
#142000
b10 3
b11001 9
b11011 7
b11010 8
b1010 ,
1'
b11010111 (
b11010111 -
#144000
0'
#146000
b11100 7
b11011 8
1'
#148000
0'
#150000
b11101 7
b11100 8
1'
#152000
b1011 ,
0'
b10001101 (
b10001101 -
#154000
b11110 7
b11101 8
1'
#156000
0'
#158000
b11111 7
b11110 8
1'
#160000
0'
#162000
b0 7
b11111 8
b1100 ,
1'
b10011100 (
b10011100 -
#164000
0'
#166000
b1 5
b1 7
b100000 8
1'
#168000
0'
#170000
b10 5
b10 7
b100001 8
1'
#172000
b1101 ,
0'
b10000101 (
b10000101 -
#174000
b11 5
b11 7
b100010 8
1'
#176000
0'
#178000
b100 5
b100 7
b100011 8
1'
#180000
0'
#182000
b101 5
b101 7
b100100 8
b1110 ,
1'
b10001010 (
b10001010 -
#184000
0'
#186000
b110 5
b110 7
b100101 8
1'
#188000
0'
#190000
b111 5
b111 7
b100110 8
1'
#192000
b1111 ,
0'
b10010001 (
b10010001 -
#194000
b1000 5
b1000 7
b100111 8
1'
#196000
0'
#198000
b1001 5
b1001 7
b101000 8
1'
#200000
0'
#202000
b1010 5
b1010 7
b101001 8
b10000 ,
1'
b10001100 (
b10001100 -
#204000
0'
#206000
b1011 5
b0 3
b101010 8
1"
1'
#208000
0'
#210000
0!
1'
#212000
b10001 ,
0'
b0 (
b0 -
#214000
1'
#216000
0'
#218000
1'
#220000
0'
#222000
b11 3
1'
1&
#224000
0'
#226000
b1 6
1#
1'
#228000
0#
0'
#230000
b10 6
1'
#232000
0'
#234000
b11 6
1'
#236000
0'
#238000
b100 6
1#
1'
#240000
0#
0'
#242000
b101 6
1#
1'
#244000
0#
0'
#246000
b110 6
1'
#248000
0'
#250000
b111 6
1'
#252000
0'
#254000
b1000 6
1#
1'
#256000
0#
0'
#258000
b1001 7
b0 6
1#
1'
#260000
0#
0'
#262000
b1 6
1#
1'
#264000
0#
0'
#266000
b10 6
1'
#268000
0'
#270000
b11 6
1'
#272000
0'
#274000
b100 6
1'
#276000
0'
#278000
b101 6
1#
1'
#280000
0#
0'
#282000
b110 6
1#
1'
#284000
0#
0'
#286000
b111 6
1'
#288000
0'
#290000
b1000 6
1'
#292000
0'
#294000
b1000 7
b0 6
1#
1'
#296000
0#
0'
#298000
b1 6
1#
1'
#300000
0#
0'
#302000
b10 6
1'
#304000
0'
#306000
b11 6
1'
#308000
0'
#310000
b100 6
1#
1'
#312000
0#
0'
#314000
b101 6
1'
#316000
0'
#318000
b110 6
1'
#320000
0'
#322000
b111 6
1'
#324000
0'
#326000
b1000 6
1#
1'
#328000
0#
0'
#330000
b111 7
b0 6
1#
1'
#332000
0#
0'
#334000
b1 6
1#
1'
#336000
0#
0'
#338000
b10 6
1'
#340000
0'
#342000
b11 6
1'
#344000
0'
#346000
b100 6
1#
1'
#348000
0#
0'
#350000
b101 6
1'
#352000
0'
#354000
b110 6
1'
#356000
0'
#358000
b111 6
1'
#360000
0'
#362000
b1000 6
1#
1'
#364000
0#
0'
#366000
b110 7
b0 6
1#
1'
#368000
0#
0'
#370000
b1 6
1#
1'
#372000
0#
0'
#374000
b10 6
1'
#376000
0'
#378000
b11 6
1'
#380000
0'
#382000
b100 6
1'
#384000
0'
#386000
b101 6
1#
1'
#388000
0#
0'
#390000
b110 6
1'
#392000
0'
#394000
b111 6
1#
1'
#396000
0#
0'
#398000
b1000 6
1'
#400000
0'
#402000
b101 7
b0 6
1#
1'
#404000
0#
0'
#406000
b1 6
1#
1'
#408000
0#
0'
#410000
b10 6
1'
#412000
0'
#414000
b11 6
1'
#416000
0'
#418000
b100 6
1'
#420000
0'
#422000
b101 6
1#
1'
#424000
0#
0'
#426000
b110 6
1'
#428000
0'
#430000
b111 6
1#
1'
#432000
0#
0'
#434000
b1000 6
1'
#436000
0'
#438000
b100 7
b0 6
1#
1'
#440000
0#
0'
#442000
b1 6
1#
1'
#444000
0#
0'
#446000
b10 6
1'
#448000
0'
#450000
b11 6
1'
#452000
0'
#454000
b100 6
1'
#456000
0'
#458000
b101 6
1#
1'
#460000
0#
0'
#462000
b110 6
1'
#464000
0'
#466000
b111 6
1#
1'
#468000
0#
0'
#470000
b1000 6
1'
#472000
0'
#474000
b11 7
b0 6
1#
1'
#476000
0#
0'
#478000
b1 6
1#
1'
#480000
0#
0'
#482000
b10 6
1'
#484000
0'
#486000
b11 6
1'
#488000
0'
#490000
b100 6
1'
#492000
0'
#494000
b101 6
1'
#496000
0'
#498000
b110 6
1#
1'
#500000
0#
0'
#502000
b111 6
1'
#504000
0'
#506000
b1000 6
1#
1'
#508000
0#
0'
#510000
b10 7
b0 6
1#
1'
#512000
0#
0'
#514000
b1 6
1#
1'
#516000
0#
0'
#518000
b10 6
1'
#520000
0'
#522000
b11 6
1'
#524000
0'
#526000
b100 6
1'
#528000
0'
#530000
b101 6
1'
#532000
0'
#534000
b110 6
1#
1'
#536000
0#
0'
#538000
b111 6
1'
#540000
0'
#542000
b1000 6
1#
1'
#544000
0#
0'
#546000
b1 7
b0 6
1#
1'
#548000
0#
0'
#550000
b1 6
1#
1'
#552000
0#
0'
#554000
b10 6
1'
#556000
0'
#558000
b11 6
1'
#560000
0'
#562000
b100 6
1#
1'
#564000
0#
0'
#566000
b101 6
1#
1'
#568000
0#
0'
#570000
b110 6
1#
1'
#572000
0#
0'
#574000
b111 6
1'
#576000
0'
#578000
b1000 6
1'
#580000
0'
#582000
b0 7
b0 6
1#
1'
#584000
0#
0'
#586000
b1 6
1#
1'
#588000
0#
0'
#590000
b10 6
1'
#592000
0'
#594000
b11 6
1'
#596000
0'
#598000
b100 6
1#
1'
#600000
0#
0'
#602000
b101 6
1#
1'
#604000
0#
0'
#606000
b110 6
1#
1'
#608000
0#
0'
#610000
b111 6
1'
#612000
0'
#614000
b1000 6
1'
#616000
0'
#618000
b11111 7
b0 6
1#
1'
#620000
0#
0'
#622000
b1 6
1#
1'
#624000
0#
0'
#626000
b10 6
1'
#628000
0'
#630000
b11 6
1'
#632000
0'
#634000
b100 6
1#
1'
#636000
0#
0'
#638000
b101 6
1#
1'
#640000
0#
0'
#642000
b110 6
1#
1'
#644000
0#
0'
#646000
b111 6
1'
#648000
0'
#650000
b1000 6
1'
#652000
0'
#654000
b11110 7
b0 6
1#
1'
#656000
0#
0'
#658000
b1 6
1#
1'
#660000
0#
0'
#662000
b10 6
1'
#664000
0'
#666000
b11 6
1'
#668000
0'
#670000
b100 6
1'
#672000
0'
#674000
b101 6
1#
1'
#676000
0#
0'
#678000
b110 6
1#
1'
#680000
0#
0'
#682000
b111 6
1'
#684000
0'
#686000
b1000 6
1#
1'
#688000
0#
0'
#690000
b11101 7
b0 6
1#
1'
#692000
0#
0'
#694000
b1 6
1#
1'
#696000
0#
0'
#698000
b10 6
1'
#700000
0'
#702000
b11 6
1'
#704000
0'
#706000
b100 6
1'
#708000
0'
#710000
b101 6
1#
1'
#712000
0#
0'
#714000
b110 6
1#
1'
#716000
0#
0'
#718000
b111 6
1'
#720000
0'
#722000
b1000 6
1#
1'
#724000
0#
0'
#726000
b11100 7
b0 6
1#
1'
#728000
0#
0'
#730000
b1 6
1#
1'
#732000
0#
0'
#734000
b10 6
1#
1'
#736000
0#
0'
#738000
b11 6
1'
#740000
0'
#742000
b100 6
1#
1'
#744000
0#
0'
#746000
b101 6
1'
#748000
0'
#750000
b110 6
1#
1'
#752000
0#
0'
#754000
b111 6
1#
1'
#756000
0#
0'
#758000
b1000 6
1#
1'
#760000
0#
0'
#762000
b11011 7
b0 6
1#
1'
#764000
0#
0'
#766000
b1 6
1#
1'
#768000
0#
0'
#770000
b10 6
1#
1'
#772000
0#
0'
#774000
b11 6
1'
#776000
0'
#778000
b100 6
1#
1'
#780000
0#
0'
#782000
b101 6
1'
#784000
0'
#786000
b110 6
1#
1'
#788000
0#
0'
#790000
b111 6
1#
1'
#792000
0#
0'
#794000
b1000 6
1#
1'
#796000
0#
0'
#798000
b11010 7
b0 6
1#
1'
#800000
0#
0'
#802000
b1 6
1#
1'
#804000
0#
0'
#806000
b10 6
1#
1'
#808000
0#
0'
#810000
b11 6
1'
#812000
0'
#814000
b100 6
1#
1'
#816000
0#
0'
#818000
b101 6
1'
#820000
0'
#822000
b110 6
1#
1'
#824000
0#
0'
#826000
b111 6
1#
1'
#828000
0#
0'
#830000
b1000 6
1#
1'
#832000
0#
0'
#834000
b11001 7
b0 6
1#
1'
#836000
0#
0'
#838000
b1 6
1#
1'
#840000
0#
0'
#842000
b10 6
1'
#844000
0'
#846000
b11 6
1'
#848000
0'
#850000
b100 6
1#
1'
#852000
0#
0'
#854000
b101 6
1#
1'
#856000
0#
0'
#858000
b110 6
1#
1'
#860000
0#
0'
#862000
b111 6
1#
1'
#864000
0#
0'
#866000
b1000 6
1#
1'
#868000
0#
0'
#870000
b11000 7
b0 6
1#
1'
#872000
0#
0'
#874000
b1 6
1#
1'
#876000
0#
0'
#878000
b10 6
1'
#880000
0'
#882000
b11 6
1'
#884000
0'
#886000
b100 6
1#
1'
#888000
0#
0'
#890000
b101 6
1#
1'
#892000
0#
0'
#894000
b110 6
1#
1'
#896000
0#
0'
#898000
b111 6
1#
1'
#900000
0#
0'
#902000
b1000 6
1#
1'
#904000
0#
0'
#906000
b10111 7
b0 6
1#
1'
#908000
0#
0'
#910000
b1 6
1#
1'
#912000
0#
0'
#914000
b10 6
1'
#916000
0'
#918000
b11 6
1'
#920000
0'
#922000
b100 6
1#
1'
#924000
0#
0'
#926000
b101 6
1'
#928000
0'
#930000
b110 6
1'
#932000
0'
#934000
b111 6
1'
#936000
0'
#938000
b1000 6
1'
#940000
0'
#942000
b10110 7
b0 6
1#
1'
#944000
0#
0'
#946000
b1 6
1#
1'
#948000
0#
0'
#950000
b10 6
1'
#952000
0'
#954000
b11 6
1'
#956000
0'
#958000
b100 6
1#
1'
#960000
0#
0'
#962000
b101 6
1'
#964000
0'
#966000
b110 6
1'
#968000
0'
#970000
b111 6
1'
#972000
0'
#974000
b1000 6
1'
#976000
0'
#978000
b10101 7
b0 6
1#
1'
#980000
0#
0'
#982000
b1 6
1#
1'
#984000
0#
0'
#986000
b10 6
1'
#988000
0'
#990000
b11 6
1'
#992000
0'
#994000
b100 6
1#
1'
#996000
0#
0'
#998000
b101 6
1'
#1000000
0'
#1002000
b110 6
1'
#1004000
0'
#1006000
b111 6
1'
#1008000
0'
#1010000
b1000 6
1'
#1012000
0'
#1014000
b10100 7
b0 6
1#
1'
#1016000
0#
0'
#1018000
b1 6
1#
1'
#1020000
0#
0'
#1022000
b10 6
1'
#1024000
0'
#1026000
b11 6
1'
#1028000
0'
#1030000
b100 6
1#
1'
#1032000
0#
0'
#1034000
b101 6
1'
#1036000
0'
#1038000
b110 6
1#
1'
#1040000
0#
0'
#1042000
b111 6
1#
1'
#1044000
0#
0'
#1046000
b1000 6
1#
1'
#1048000
0#
0'
#1050000
b10011 7
b0 6
1#
1'
#1052000
0#
0'
#1054000
b1 6
1#
1'
#1056000
0#
0'
#1058000
b10 6
1'
#1060000
0'
#1062000
b11 6
1'
#1064000
0'
#1066000
b100 6
1#
1'
#1068000
0#
0'
#1070000
b101 6
1'
#1072000
0'
#1074000
b110 6
1#
1'
#1076000
0#
0'
#1078000
b111 6
1#
1'
#1080000
0#
0'
#1082000
b1000 6
1#
1'
#1084000
0#
0'
#1086000
b10010 7
b0 6
1#
1'
#1088000
0#
0'
#1090000
b1 6
1#
1'
#1092000
0#
0'
#1094000
b10 6
1#
1'
#1096000
0#
0'
#1098000
b11 6
1'
#1100000
0'
#1102000
b100 6
1#
1'
#1104000
0#
0'
#1106000
b101 6
1'
#1108000
0'
#1110000
b110 6
1#
1'
#1112000
0#
0'
#1114000
b111 6
1'
#1116000
0'
#1118000
b1000 6
1#
1'
#1120000
0#
0'
#1122000
b10001 7
b0 6
1#
1'
#1124000
0#
0'
#1126000
b1 6
1#
1'
#1128000
0#
0'
#1130000
b10 6
1#
1'
#1132000
0#
0'
#1134000
b11 6
1'
#1136000
0'
#1138000
b100 6
1#
1'
#1140000
0#
0'
#1142000
b101 6
1'
#1144000
0'
#1146000
b110 6
1#
1'
#1148000
0#
0'
#1150000
b111 6
1'
#1152000
0'
#1154000
b1000 6
1#
1'
#1156000
0#
0'
#1158000
b10000 7
b0 6
1#
1'
#1160000
0#
0'
#1162000
b1 6
1#
1'
#1164000
0#
0'
#1166000
b10 6
1#
1'
#1168000
0#
0'
#1170000
b11 6
1'
#1172000
0'
#1174000
b100 6
1#
1'
#1176000
0#
0'
#1178000
b101 6
1'
#1180000
0'
#1182000
b110 6
1#
1'
#1184000
0#
0'
#1186000
b111 6
1'
#1188000
0'
#1190000
b1000 6
1#
1'
#1192000
0#
0'
#1194000
b1111 7
b0 6
1#
1'
#1196000
0#
0'
#1198000
b1 6
1#
1'
#1200000
0#
0'
#1202000
b10 6
1'
#1204000
0'
#1206000
b11 6
1'
#1208000
0'
#1210000
b100 6
1#
1'
#1212000
0#
0'
#1214000
b101 6
1'
#1216000
0'
#1218000
b110 6
1'
#1220000
0'
#1222000
b111 6
1#
1'
#1224000
0#
0'
#1226000
b1000 6
1#
1'
#1228000
0#
0'
#1230000
b1110 7
b0 6
1#
1'
#1232000
0#
0'
#1234000
b1 6
1#
1'
#1236000
0#
0'
#1238000
b10 6
1'
#1240000
0'
#1242000
b11 6
1'
#1244000
0'
#1246000
b100 6
1#
1'
#1248000
0#
0'
#1250000
b101 6
1'
#1252000
0'
#1254000
b110 6
1'
#1256000
0'
#1258000
b111 6
1#
1'
#1260000
0#
0'
#1262000
b1000 6
1#
1'
#1264000
0#
0'
#1266000
b1101 7
b0 6
1#
1'
#1268000
0#
0'
#1270000
b1 6
1#
1'
#1272000
0#
0'
#1274000
b10 6
1'
#1276000
0'
#1278000
b11 6
1'
#1280000
0'
#1282000
b100 6
1#
1'
#1284000
0#
0'
#1286000
b101 6
1#
1'
#1288000
0#
0'
#1290000
b110 6
1'
#1292000
0'
#1294000
b111 6
1#
1'
#1296000
0#
0'
#1298000
b1000 6
1#
1'
#1300000
0#
0'
#1302000
b1100 7
b0 6
1#
1'
#1304000
0#
0'
#1306000
b1 6
1#
1'
#1308000
0#
0'
#1310000
b10 6
1'
#1312000
0'
#1314000
b11 6
1'
#1316000
0'
#1318000
b100 6
1#
1'
#1320000
0#
0'
#1322000
b101 6
1#
1'
#1324000
0#
0'
#1326000
b110 6
1'
#1328000
0'
#1330000
b111 6
1#
1'
#1332000
0#
0'
#1334000
b1000 6
1#
1'
#1336000
0#
0'
#1338000
b1011 7
b0 6
1#
1'
#1340000
0#
0'
#1342000
b0 3
1$
1'
